mypackage/__init__.py
mypackage/api.py
mypackage/core_logic.pyd
none555_secretpkg_demo-0.1.0.dist-info/LICENSE
none555_secretpkg_demo-0.1.0.dist-info/METADATA
none555_secretpkg_demo-0.1.0.dist-info/WHEEL
none555_secretpkg_demo-0.1.0.dist-info/top_level.txt
none555_secretpkg_demo-0.1.0.dist-info/RECORD
