Metadata-Version: 2.1
Name: none555-secretpkg-demo
Version: 0.1.0
Summary: 一个带有二进制保护的Python包
Author: Your Name
Author-email: Your Name <your.email@example.com>
License: MIT
Project-URL: Homepage, https://github.com/yourusername/mypackage
Project-URL: Repository, https://github.com/yourusername/mypackage.git
Project-URL: Issues, https://github.com/yourusername/mypackage/issues
Classifier: Development Status :: 3 - Alpha
Classifier: Intended Audience :: Developers
Classifier: License :: OSI Approved :: MIT License
Classifier: Programming Language :: Python :: 3
Classifier: Programming Language :: Python :: 3.7
Classifier: Programming Language :: Python :: 3.8
Classifier: Programming Language :: Python :: 3.9
Classifier: Programming Language :: Python :: 3.10
Classifier: Programming Language :: Python :: 3.11
Requires-Python: >=3.7
License-File: LICENSE
Requires-Dist: nuitka>=1.8.0
